README.rst
setup.py
omnigraffle_export/__init__.py
omnigraffle_export/omnigraffle.py
omnigraffle_export/omnigraffle_export.py
omnigraffle_export.egg-info/PKG-INFO
omnigraffle_export.egg-info/SOURCES.txt
omnigraffle_export.egg-info/dependency_links.txt
omnigraffle_export.egg-info/entry_points.txt
omnigraffle_export.egg-info/requires.txt
omnigraffle_export.egg-info/top_level.txt
omnigraffle_export.egg-info/zip-safe
tests/__init__.py
tests/test_omnigraffle_export.py