Metadata-Version: 1.1
Name: omnigraffle-export
Version: 1.6
Summary: A command line utility that exports omnigraffle canvases files into various formats.
Home-page: https://github.com/fikovnik/omnigraffle-export
Author: Filip Krikava
Author-email: krikava@gmail.com
License: http://www.opensource.org/licenses/mit-license.php
Keywords: omnigraffle export
Platform: UNKNOWN
Classifier: Development Status :: 5 - Production/Stable
Classifier: Operating System :: MacOS :: MacOS X
Classifier: Environment :: Console
Classifier: License :: OSI Approved :: MIT License
Classifier: Programming Language :: Python :: 2.7
Classifier: Topic :: Utilities
